Metadata-Version: 1.0
Name: gauss-binomial-mp99
Version: 0.1
Summary: Gaussian and Binomial distributions
Home-page: UNKNOWN
Author: Manan Paneri
Author-email: mananpaneri28@gmail.com
License: UNKNOWN
Platform: UNKNOWN
